setup.cfg
setup.py
GeoAlchemy.egg-info/PKG-INFO
GeoAlchemy.egg-info/SOURCES.txt
GeoAlchemy.egg-info/dependency_links.txt
GeoAlchemy.egg-info/entry_points.txt
GeoAlchemy.egg-info/not-zip-safe
GeoAlchemy.egg-info/requires.txt
GeoAlchemy.egg-info/top_level.txt
geoalchemy/__init__.py
geoalchemy/base.py
geoalchemy/dialect.py
geoalchemy/functions.py
geoalchemy/geometry.py
geoalchemy/mssql.py
geoalchemy/mysql.py
geoalchemy/oracle.py
geoalchemy/postgis.py
geoalchemy/spatialite.py
geoalchemy/utils.py
geoalchemy/tests/__init__.py
geoalchemy/tests/test_dialect.py
geoalchemy/tests/test_mssql.py
geoalchemy/tests/test_mysql.py
geoalchemy/tests/test_oracle.py
geoalchemy/tests/test_postgis.py
geoalchemy/tests/test_spatialite.py
geoalchemy/tests/test_type.py