Metadata-Version: 1.0
Name: GeoAlchemy
Version: 0.7
Summary: Using SQLAlchemy with Spatial Databases
Home-page: http://geoalchemy.org/
Author: Eric Lemoine
Author-email: eric.lemoine@camptocamp.com
License: MIT
Keywords: geo gis sqlalchemy orm
Platform: UNKNOWN
Classifier: Development Status :: 3 - Alpha
Classifier: Environment :: Plugins
Classifier: Operating System :: OS Independent
Classifier: Programming Language :: Python
Classifier: Intended Audience :: Information Technology
Classifier: License :: OSI Approved :: MIT License
Classifier: Topic :: Scientific/Engineering :: GIS
